pyt_pacakge/__init__.py
pyt_pacakge/ust_alma.py
ust_alma-0.0.1.dist-info/LICENSE
ust_alma-0.0.1.dist-info/METADATA
ust_alma-0.0.1.dist-info/WHEEL
ust_alma-0.0.1.dist-info/top_level.txt
ust_alma-0.0.1.dist-info/RECORD
