Metadata-Version: 2.1
Name: ust-alma
Version: 0.0.1
Summary: Pip Create
Home-page: https://github.com/pypa/sampleproject
Author: Abdurrahman
Author-email: abdurrahmanpulat9@gmail.com
Project-URL: Bug Tracker, https://github.com/pypa/sampleproject/issues
Classifier: Programming Language :: Python :: 3
Classifier: License :: OSI Approved :: MIT License
Classifier: Operating System :: OS Independent
Requires-Python: >=3.6
License-File: LICENSE
